odoo/addons/account_invoice_change_currency/README.rst
odoo/addons/account_invoice_change_currency/__init__.py
odoo/addons/account_invoice_change_currency/__manifest__.py
odoo/addons/account_invoice_change_currency/data/ir_server_actions.xml
odoo/addons/account_invoice_change_currency/data/message_subtype.xml
odoo/addons/account_invoice_change_currency/i18n/account_invoice_change_currency.pot
odoo/addons/account_invoice_change_currency/i18n/de.po
odoo/addons/account_invoice_change_currency/models/__init__.py
odoo/addons/account_invoice_change_currency/models/account_change_currency.py
odoo/addons/account_invoice_change_currency/readme/CONFIGURE.rst
odoo/addons/account_invoice_change_currency/readme/CONTRIBUTORS.rst
odoo/addons/account_invoice_change_currency/readme/DESCRIPTION.rst
odoo/addons/account_invoice_change_currency/readme/USAGE.rst
odoo/addons/account_invoice_change_currency/static/description/icon.png
odoo/addons/account_invoice_change_currency/static/description/index.html
odoo/addons/account_invoice_change_currency/tests/__init__.py
odoo/addons/account_invoice_change_currency/tests/test_account_invoice_change_currency.py
odoo/addons/account_invoice_change_currency/views/account_invoice.xml
odoo11_addon_account_invoice_change_currency-11.0.1.0.0.99.dev22.dist-info/METADATA
odoo11_addon_account_invoice_change_currency-11.0.1.0.0.99.dev22.dist-info/WHEEL
odoo11_addon_account_invoice_change_currency-11.0.1.0.0.99.dev22.dist-info/top_level.txt
odoo11_addon_account_invoice_change_currency-11.0.1.0.0.99.dev22.dist-info/RECORD
